{
  "display": {
    "icon": {
      "item": "elementaristics:essence",
      "data": 9
    },
    "title": {
      "translate": "advancement.elementaristics.body"
    },
    "description": {
      "translate": ""
    }
  },
  "parent": "elementaristics:discovery_earth",
  "criteria": {
    "book": {
      "trigger": "minecraft:inventory_changed",
      "conditions": {
        "items": [
          {
            "item": "elementaristics:essence",
            "data": 9
          }
        ]
      }
    }
  }
}